sphinx_tojupyter/__init__.py
sphinx_tojupyter/builders/__init__.py
sphinx_tojupyter/builders/jupyter.py
sphinx_tojupyter/builders/jupyterpdf.py
sphinx_tojupyter/directive/__init__.py
sphinx_tojupyter/directive/jupyter.py
sphinx_tojupyter/writers/__init__.py
sphinx_tojupyter/writers/convert.py
sphinx_tojupyter/writers/execute_nb.py
sphinx_tojupyter/writers/jupyter.py
sphinx_tojupyter/writers/make_pdf.py
sphinx_tojupyter/writers/make_site.py
sphinx_tojupyter/writers/translate_all.py
sphinx_tojupyter/writers/translate_code.py
sphinx_tojupyter/writers/utils.py
sphinx_tojupyter-0.6.0.dist-info/licenses/LICENSE
sphinx_tojupyter-0.6.0.dist-info/METADATA
sphinx_tojupyter-0.6.0.dist-info/WHEEL
sphinx_tojupyter-0.6.0.dist-info/top_level.txt
sphinx_tojupyter-0.6.0.dist-info/RECORD
